arrrgs/__init__.py
arrrgs/arguments.py
arrrgs/command.py
arrrgs/log.py
arrrgs/parser.py
arrrgs/run.py
arrrgs-3.1.0.dist-info/LICENSE
arrrgs-3.1.0.dist-info/METADATA
arrrgs-3.1.0.dist-info/WHEEL
arrrgs-3.1.0.dist-info/top_level.txt
arrrgs-3.1.0.dist-info/RECORD
