Metadata-Version: 2.1
Name: arrrgs
Version: 3.1.0
Summary: The library for easily writing feature-rich Python scripts
Author-email: Mikhael Khrustik <misha@myrt.co>
License: MIT
Keywords: cli,command-line-tool
Classifier: Programming Language :: Python :: 3
Classifier: License :: OSI Approved :: MIT License
Requires-Python: >=3.7
License-File: LICENSE
Requires-Dist: argparse
